setup.py
pyrtd.egg-info/PKG-INFO
pyrtd.egg-info/SOURCES.txt
pyrtd.egg-info/dependency_links.txt
pyrtd.egg-info/top_level.txt
rtd/__init__.py
rtd/client.py